<?xml version="1.0" encoding="UTF-8"?>
<objects serializationModel="Studio.01.10.00">
    <object class="AudioFile" id="{fd3c1a4d-97f4-4dbd-8399-b3eb0b3b03d8}">
        <property name="assetPath">
            <value>Beast Soft Roar.mp3</value>
        </property>
        <property name="frequencyInKHz">
            <value>44.0999985</value>
        </property>
        <property name="channelCount">
            <value>2</value>
        </property>
        <property name="length">
            <value>6.6089795918367349</value>
        </property>
        <relationship name="masterAssetFolder">
            <destination>{99efb5cd-ee04-46a8-bb75-0277c5996dd0}</destination>
        </relationship>
    </object>
</objects>
